opal/__init__.py
opal/conf.py
opal/evaluate.py
opal/models/2023.9.4/2023_09_01_performance_mania_top_10000_20230904212037.csv/lightning_logs/version_20/evaluation/model.ckpt
opal/models/README.md
opal/module/__init__.py
opal/module/opal_net.py
opal/module/opal_net_module.py
opal/score_datamodule.py
opal/svness.py
opal/train.py
opal_net-2023.9.4.dist-info/METADATA
opal_net-2023.9.4.dist-info/WHEEL
opal_net-2023.9.4.dist-info/RECORD
